fastapi_abc/__init__.py
fastapi_abc/baseclasses.py
fastapi_abc/structures.py
fastapi_abc-0.1.0.dist-info/METADATA
fastapi_abc-0.1.0.dist-info/WHEEL
fastapi_abc-0.1.0.dist-info/entry_points.txt
fastapi_abc-0.1.0.dist-info/RECORD
